genomeuploader/__init__.py
genomeuploader/cluster_uploader_wrapper.py
genomeuploader/constants.py
genomeuploader/ena.py
genomeuploader/genome_upload.py
genomeuploader-2.0.0.dist-info/LICENSE.md
genomeuploader-2.0.0.dist-info/METADATA
genomeuploader-2.0.0.dist-info/WHEEL
genomeuploader-2.0.0.dist-info/entry_points.txt
genomeuploader-2.0.0.dist-info/top_level.txt
genomeuploader-2.0.0.dist-info/RECORD
