Metadata-Version: 2.1
Name: genomeuploader
Version: 2.0.0
Summary: Python script to upload bins and MAGs in fasta format to ENA (European Nucleotide Archive). This script generates xmls and manifests necessary for submission with webin-cli.
Author-email: MGnify team <metagenomics-help@ebi.ac.uk>
License: Apache Software License 2.0
Keywords: bioinformatics,tool,metagenomics
Classifier: Programming Language :: Python :: 3.8
Classifier: Programming Language :: Python :: 3.9
Classifier: Programming Language :: Python :: 3.10
Classifier: Development Status :: 5 - Production/Stable
Classifier: Intended Audience :: Science/Research
Classifier: Topic :: Scientific/Engineering :: Bio-Informatics
Classifier: License :: OSI Approved :: Apache Software License
Classifier: Operating System :: OS Independent
Requires-Python: >=3.8
License-File: LICENSE.md
Requires-Dist: requests ==2.26.0
Requires-Dist: pandas ==1.4.1
Requires-Dist: python-dotenv ==1.0.1
Provides-Extra: dev
Requires-Dist: pre-commit ==3.3.3 ; extra == 'dev'
Requires-Dist: black ==23.7.0 ; extra == 'dev'
Requires-Dist: ruff ==v0.0.286 ; extra == 'dev'
Requires-Dist: isort ==5.12.0 ; extra == 'dev'
Requires-Dist: bump-my-version ==0.9.2 ; extra == 'dev'
Provides-Extra: test
Requires-Dist: pytest ==7.1.2 ; extra == 'test'
Requires-Dist: pytest-cov ==3.0.0 ; extra == 'test'
